plex_nfs_watchdog/__init__.py
plex_nfs_watchdog/plex_nfs_watchdog.py
plex_nfs_watchdog/modules/__init__.py
plex_nfs_watchdog/modules/cli/__init__.py
plex_nfs_watchdog/modules/cli/helper.py
plex_nfs_watchdog/modules/config/__init__.py
plex_nfs_watchdog/modules/config/shared.py
plex_nfs_watchdog/modules/plex/__init__.py
plex_nfs_watchdog/modules/plex/plex_agent.py
plex_nfs_watchdog/modules/watchdog/__init__.py
plex_nfs_watchdog/modules/watchdog/plex_watchdog_event.py
plex_nfs_watchdog-0.0.16.dist-info/licenses/LICENSE
plex_nfs_watchdog-0.0.16.dist-info/METADATA
plex_nfs_watchdog-0.0.16.dist-info/WHEEL
plex_nfs_watchdog-0.0.16.dist-info/entry_points.txt
plex_nfs_watchdog-0.0.16.dist-info/top_level.txt
plex_nfs_watchdog-0.0.16.dist-info/RECORD
