Metadata-Version: 2.4
Name: plex-nfs-watchdog
Version: 0.0.16
Summary: A utility to trigger Plex partial-scans on NFS configurations, on which inotify is not supported
Home-page: https://github.com/LightDestory/PlexNFSWatchdog
Author: LightDestory
Author-email: apb231@gmail.com
Project-URL: Bug Tracker, https://github.com/LightDestory/PlexNFSWatchdog/issues
Classifier: Development Status :: 5 - Production/Stable
Classifier: Environment :: Console
Classifier: Operating System :: OS Independent
Classifier: Programming Language :: Python :: 3.9
Classifier: Programming Language :: Python :: 3.10
Classifier: Programming Language :: Python :: 3.11
Classifier: Programming Language :: Python :: 3.12
Classifier: Programming Language :: Python :: 3.13
Classifier: Typing :: Typed
Requires-Python: >=3.9
License-File: LICENSE
Requires-Dist: plexapi~=4.16.1
Requires-Dist: watchdog~=6.0.0
Requires-Dist: colorlog~=6.9.0
Dynamic: license-file
